MANIFEST.in
README.md
pyproject.toml
setup.py
version
ScalaProcessUtils/__init__.py
e2eAIOK_recdp.egg-info/PKG-INFO
e2eAIOK_recdp.egg-info/SOURCES.txt
e2eAIOK_recdp.egg-info/dependency_links.txt
e2eAIOK_recdp.egg-info/not-zip-safe
e2eAIOK_recdp.egg-info/requires.txt
e2eAIOK_recdp.egg-info/top_level.txt
pyrecdp/__init__.py
pyrecdp/LLM/TextPipeline.py
pyrecdp/LLM/__init__.py
pyrecdp/LLM/requirements.txt
pyrecdp/ScalaProcessUtils/__init__.py
pyrecdp/ScalaProcessUtils/spark-defaults.conf
pyrecdp/ScalaProcessUtils/spark-env.sh
pyrecdp/ScalaProcessUtils/target/recdp-scala-extensions-0.1.0-jar-with-dependencies.jar
pyrecdp/autofe/AutoFE.py
pyrecdp/autofe/FeatureEstimator.py
pyrecdp/autofe/FeatureProfiler.py
pyrecdp/autofe/FeatureWrangler.py
pyrecdp/autofe/RelationalBuilder.py
pyrecdp/autofe/TabularPipeline.py
pyrecdp/autofe/__init__.py
pyrecdp/autofe/requirements.txt
pyrecdp/core/__init__.py
pyrecdp/core/cache_utils.py
pyrecdp/core/class_utils.py
pyrecdp/core/dataframe.py
pyrecdp/core/di_graph.py
pyrecdp/core/import_utils.py
pyrecdp/core/model_utils.py
pyrecdp/core/parallel_iterator.py
pyrecdp/core/pipeline.py
pyrecdp/core/registry.py
pyrecdp/core/schema.py
pyrecdp/core/utils.py
pyrecdp/datasets/__init__.py
pyrecdp/datasets/base_api.py
pyrecdp/datasets/download.py
pyrecdp/primitives/__init__.py
pyrecdp/primitives/document/__init__.py
pyrecdp/primitives/estimators/__init__.py
pyrecdp/primitives/estimators/base.py
pyrecdp/primitives/estimators/lightgbm.py
pyrecdp/primitives/generators/__init__.py
pyrecdp/primitives/generators/base.py
pyrecdp/primitives/generators/binned.py
pyrecdp/primitives/generators/category.py
pyrecdp/primitives/generators/datetime.py
pyrecdp/primitives/generators/drop.py
pyrecdp/primitives/generators/encode.py
pyrecdp/primitives/generators/feature_transform.py
pyrecdp/primitives/generators/featuretools_adaptor.py
pyrecdp/primitives/generators/fillna.py
pyrecdp/primitives/generators/geograph.py
pyrecdp/primitives/generators/group_category.py
pyrecdp/primitives/generators/name.py
pyrecdp/primitives/generators/nlp.py
pyrecdp/primitives/generators/relation.py
pyrecdp/primitives/generators/type.py
pyrecdp/primitives/llmutils/__init__.py
