Metadata-Version: 2.1
Name: e2eAIOK-recdp
Version: 1.2.0
Summary: A data processing bundle for spark based recommender system operations
Home-page: https://github.com/intel/e2eAIOK/
Author: INTEL BDF AIOK
Author-email: bdf.aiok@intel.com
License: UNKNOWN
Project-URL: Bug Tracker, https://github.com/intel/e2eAIOK/
Keywords: pyrecdp recdp distributed parallel auto-feature-engineering autofe LLM python
Platform: UNKNOWN
Classifier: Programming Language :: Python :: 3
Classifier: License :: OSI Approved :: Apache Software License
Classifier: Operating System :: OS Independent
Requires-Python: >=3.6
Provides-Extra: autofe
Provides-Extra: LLM
Provides-Extra: all
